RMTfunc/__init__.py
RMTfunc/utils.py
RMTfunc-0.1.dev0.dist-info/LICENSE
RMTfunc-0.1.dev0.dist-info/METADATA
RMTfunc-0.1.dev0.dist-info/WHEEL
RMTfunc-0.1.dev0.dist-info/top_level.txt
RMTfunc-0.1.dev0.dist-info/RECORD
