Metadata-Version: 2.1
Name: RMTfunc
Version: 0.1.dev0
Summary: Eigenvalue unfolding and spectral observable computation
Home-page: https://github.com/stfxecutables/empyricalRMT
Author: Derek Berger
Author-email: dmberger.dev@gmail.com
Maintainer: Derek Berger
License: MIT
Keywords: RMT RandomMatrixTheory spectral observabales eigenvalues unfolding
Platform: UNKNOWN
Classifier: Programming Language :: Python :: 3
Classifier: License :: OSI Approved :: MIT License
Classifier: Operating System :: OS Independent
Classifier: Development Status :: 3 - Alpha
Requires-Python: >=3
Requires-Dist: colorama
Requires-Dist: EMD-signal
Requires-Dist: empyricalRMT
Requires-Dist: multiprocess
Requires-Dist: nibabel
Requires-Dist: nilearn
Requires-Dist: numba
Requires-Dist: numpy
Requires-Dist: progressbar
Requires-Dist: scipy
